chart/__init__.py
chart/bar.py
chart/preprocessing.py
chart/scatter.py
chart-0.1.0.dist-info/LICENSE
chart-0.1.0.dist-info/METADATA
chart-0.1.0.dist-info/WHEEL
chart-0.1.0.dist-info/top_level.txt
chart-0.1.0.dist-info/RECORD
