Metadata-Version: 2.1
Name: chart
Version: 0.1.0
Summary: chart
Home-page: https://github.com/maxhumber/chart
Author: Max Humber
Author-email: max.humber@gmail.com
License: MIT
Keywords: chart,graph,bar,scatter,visualization
Platform: UNKNOWN
Classifier: Development Status :: 2 - Pre-Alpha
Classifier: License :: OSI Approved :: MIT License
Classifier: Programming Language :: Python :: 3
Requires-Python: >=3.6
